stackio
