Metadata-Version: 1.0
Name: stack.io
Version: 0.1.1
Summary: A language-agnostic framework for distributed and authenticated communication between web and back-end clients.
Home-page: https://github.com/dotcloud/stack.io-python
Author: dotCloud, Inc.
Author-email: UNKNOWN
License: MIT
Platform: UNKNOWN
